pymoors-0.2.5.dist-info/METADATA
pymoors-0.2.5.dist-info/WHEEL
pymoors-0.2.5.dist-info/licenses/LICENSE
pymoors/__init__.py
pymoors/_pymoors.cpython-312-darwin.so
pymoors/_pymoors.pyi
pymoors/constraints.py
pymoors/py.typed
pymoors/schemas.py
pymoors/typing.py
pymoors-0.2.5.dist-info/RECORD
