Metadata-Version: 2.4
Name: pymoors
Version: 0.2.5
Classifier: Programming Language :: Python
Classifier: Programming Language :: Python :: 3
Classifier: Programming Language :: Python :: 3 :: Only
Classifier: Programming Language :: Python :: 3.10
Classifier: Programming Language :: Python :: 3.11
Classifier: Programming Language :: Python :: 3.12
Classifier: Programming Language :: Python :: 3.13
Classifier: Programming Language :: Rust
Classifier: Intended Audience :: Developers
Classifier: Intended Audience :: Information Technology
Classifier: License :: OSI Approved :: MIT License
Classifier: Typing :: Typed
Requires-Dist: numpy>=2.0.0
License-File: LICENSE
Author-email: Andrés Sandoval <andres.sndbrca@gmail.com>
Requires-Python: >=3.10
